{"strategy": [{"Driver": "VER", "Stint": 2.0, "Compound": "MEDIUM", "LapStart": 45.0, "FinishOrder": 1, "LapEnd": 57.0, "fill": "yellow"}, {"Driver": "VER", "Stint": 1.0, "Compound": "HARD", "LapStart": 0.0, "FinishOrder": 1, "LapEnd": 45.0, "fill": "white"}, {"Driver": "PER", "Stint": 2.0, "Compound": "HARD", "LapStart": 20.0, "FinishOrder": 2, "LapEnd": 57.0, "fill": "white"}, {"Driver": "PER", "Stint": 1.0, "Compound": "MEDIUM", "LapStart": 0.0, "FinishOrder": 2, "LapEnd": 20.0, "fill": "yellow"}, {"Driver": "ALO", "Stint": 1.0, "Compound": "MEDIUM", "LapStart": 0.0, "FinishOrder": 3, "LapEnd": 24.0, "fill": "yellow"}, {"Driver": "ALO", "Stint": 2.0, "Compound": "HARD", "LapStart": 24.0, "FinishOrder": 3, "LapEnd": 57.0, "fill": "white"}, {"Driver": "RUS", "Stint": 2.0, "Compound": "HARD", "LapStart": 17.0, "FinishOrder": 4, "LapEnd": 57.0, "fill": "white"}, {"Driver": "RUS", "Stint": 1.0, "Compound": "MEDIUM", "LapStart": 0.0, "FinishOrder": 4, "LapEnd": 17.0, "fill": "yellow"}, {"Driver": "SAI", "Stint": 2.0, "Compound": "HARD", "LapStart": 18.0, "FinishOrder": 5, "LapEnd": 57.0, "fill": "white"}, {"Driver": "SAI", "Stint": 1.0, "Compound": "MEDIUM", "LapStart": 0.0, "FinishOrder": 5, "LapEnd": 18.0, "fill": "yellow"}, {"Driver": "HAM", "Stint": 1.0, "Compound": "HARD", "LapStart": 0.0, "FinishOrder": 6, "LapEnd": 37.0, "fill": "white"}, {"Driver": "HAM", "Stint": 2.0, "Compound": "MEDIUM", "LapStart": 37.0, "FinishOrder": 6, "LapEnd": 57.0, "fill": "yellow"}, {"Driver": "LEC", "Stint": 2.0, "Compound": "HARD", "LapStart": 17.0, "FinishOrder": 7, "LapEnd": 57.0, "fill": "white"}, {"Driver": "LEC", "Stint": 1.0, "Compound": "MEDIUM", "LapStart": 0.0, "FinishOrder": 7, "LapEnd": 17.0, "fill": "yellow"}, {"Driver": "GAS", "Stint": 2.0, "Compound": "HARD", "LapStart": 15.0, "FinishOrder": 8, "LapEnd": 57.0, "fill": "white"}, {"Driver": "GAS", "Stint": 1.0, "Compound": "MEDIUM", "LapStart": 0.0, "FinishOrder": 8, "LapEnd": 15.0, "fill": "yellow"}, {"Driver": "OCO", "Stint": 1.0, "Compound": "HARD", "LapStart": 0.0, "FinishOrder": 9, "LapEnd": 39.0, "fill": "white"}, {"Driver": "OCO", "Stint": 2.0, "Compound": "MEDIUM", "LapStart": 39.0, "FinishOrder": 9, "LapEnd": 57.0, "fill": "yellow"}, {"Driver": "MAG", "Stint": 1.0, "Compound": "MEDIUM", "LapStart": 0.0, "FinishOrder": 10, "LapEnd": 14.0, "fill": "yellow"}, {"Driver": "MAG", "Stint": 2.0, "Compound": "HARD", "LapStart": 14.0, "FinishOrder": 10, "LapEnd": 57.0, "fill": "white"}, {"Driver": "TSU", "Stint": 2.0, "Compound": "MEDIUM", "LapStart": 36.0, "FinishOrder": 11, "LapEnd": 57.0, "fill": "yellow"}, {"Driver": "TSU", "Stint": 1.0, "Compound": "HARD", "LapStart": 0.0, "FinishOrder": 11, "LapEnd": 36.0, "fill": "white"}, {"Driver": "STR", "Stint": 2.0, "Compound": "MEDIUM", "LapStart": 42.0, "FinishOrder": 12, "LapEnd": 57.0, "fill": "yellow"}, {"Driver": "STR", "Stint": 1.0, "Compound": "HARD", "LapStart": 0.0, "FinishOrder": 12, "LapEnd": 42.0, "fill": "white"}, {"Driver": "BOT", "Stint": 2.0, "Compound": "HARD", "LapStart": 15.0, "FinishOrder": 13, "LapEnd": 57.0, "fill": "white"}, {"Driver": "BOT", "Stint": 1.0, "Compound": "MEDIUM", "LapStart": 0.0, "FinishOrder": 13, "LapEnd": 15.0, "fill": "yellow"}, {"Driver": "ALB", "Stint": 2.0, "Compound": "HARD", "LapStart": 22.0, "FinishOrder": 14, "LapEnd": 57.0, "fill": "white"}, {"Driver": "ALB", "Stint": 1.0, "Compound": "MEDIUM", "LapStart": 0.0, "FinishOrder": 14, "LapEnd": 22.0, "fill": "yellow"}, {"Driver": "HUL", "Stint": 1.0, "Compound": "HARD", "LapStart": 0.0, "FinishOrder": 15, "LapEnd": 33.0, "fill": "white"}, {"Driver": "HUL", "Stint": 2.0, "Compound": "MEDIUM", "LapStart": 33.0, "FinishOrder": 15, "LapEnd": 57.0, "fill": "yellow"}, {"Driver": "ZHO", "Stint": 2.0, "Compound": "MEDIUM", "LapStart": 31.0, "FinishOrder": 16, "LapEnd": 57.0, "fill": "yellow"}, {"Driver": "ZHO", "Stint": 1.0, "Compound": "HARD", "LapStart": 0.0, "FinishOrder": 16, "LapEnd": 31.0, "fill": "white"}, {"Driver": "NOR", "Stint": 1.0, "Compound": "SOFT", "LapStart": 0.0, "FinishOrder": 17, "LapEnd": 4.0, "fill": "red"}, {"Driver": "NOR", "Stint": 2.0, "Compound": "HARD", "LapStart": 4.0, "FinishOrder": 17, "LapEnd": 57.0, "fill": "white"}, {"Driver": "DEV", "Stint": 2.0, "Compound": "HARD", "LapStart": 15.0, "FinishOrder": 18, "LapEnd": 57.0, "fill": "white"}, {"Driver": "DEV", "Stint": 1.0, "Compound": "MEDIUM", "LapStart": 0.0, "FinishOrder": 18, "LapEnd": 15.0, "fill": "yellow"}, {"Driver": "PIA", "Stint": 2.0, "Compound": "HARD", "LapStart": 5.0, "FinishOrder": 19, "LapEnd": 56.0, "fill": "white"}, {"Driver": "PIA", "Stint": 1.0, "Compound": "SOFT", "LapStart": 0.0, "FinishOrder": 19, "LapEnd": 5.0, "fill": "red"}, {"Driver": "SAR", "Stint": 2.0, "Compound": "HARD", "LapStart": 2.0, "FinishOrder": 20, "LapEnd": 56.0, "fill": "white"}, {"Driver": "SAR", "Stint": 1.0, "Compound": "MEDIUM", "LapStart": 0.0, "FinishOrder": 20, "LapEnd": 2.0, "fill": "yellow"}]}